{"CreateTimeStamp":"2023-04-26T17:51:15.6887609+09:00","From":"ガーデンスパ十勝川温泉","To":"しほろ温泉","Title":"道道316号","DistanceMeters":35010,"Duration":"00:36:10","Polyline":"}m`eGsjsiZDMFFNLVTVRZXCJ_@`ASh@CFM\\a@~@a@dAIRiAvCEJEJGTOf@Uz@AFUrAERALSdAc@fCw@e@a@UGCQGME[IKCKAMAA?W?O?a@DYFYHKFc@Tc@ZqAhAYRQPsBfBi@f@URcBxAaBvA_@`@ON]^k@|@]j@u@tAAB_@n@KNEDE@[j@GLwAdCo@hAOV]n@aBpCOZQd@O`@Wv@ER[xAAFMj@Kb@AHKd@Qr@EHGNKZUf@Q`@KPa@x@]l@w@|AYf@CFYd@U\\KLABEFs@v@y@r@q@l@WTw@t@gA`Am@n@ABY\\?@Y`@EDSZ]h@S\\Wd@OV]p@KTa@x@o@fAk@x@]f@]`@EFSVMLq@p@MJ_@\\]XGD[TYP[Tc@VIDi@VWJGB]L_@LQDa@LQDa@JG@_B`@C@w@ReAVs@Ps@Lm@La@JE@]HWFiAVk@N[J]FA@K@KBWD]Ba@BM@O?M?g@?g@CeAIu@MWGMCo@Qi@SECKGWKGA_@QIEGCg@S_@Mk@IUEKAi@AQ?M?k@Bs@PmB\\{Cv@{AX{Cl@eANI?G?_@?[ICA[KECWQc@_@CC_@i@[m@gAqCsA{Co@gAu@cAs@{@uAcB]a@Y[[USMGEQMWKSIUIYIe@KWCc@CY?[@u@Dc@Bc@Bc@BE?gGb@iG`@Q@[Bu@Fu@Ds@Fe@Bc@Bc@DG?YBS@a@Bu@Fk@DI?u@Fc@BeAHu@DYB]Bi@BI@}@DK@s@DqCToCPwAD{ABiCHe@Be@@W@O@O@iABiAB_@@e@DM@e@JE?k@PQFIBaBr@}@\\i@T{Ap@q@ZcAb@C@uB|@uB~@s@XYNULKJQLWZOVQ\\KTIRGVMl@Kh@Kl@Kl@Kl@EVETKn@Kn@q@lEGTGVGRIRCHEHKRINMPKNMNMLOLMJC@KFOHC@E@GBGBGBE?C@G@UDM@Q@O@QAUAWEYGy@WoBo@[IYE_@ESAc@AG@[@]DWF_@Ja@PcDzA{At@m@X[LSHMBSBS@S?M?OCy@KuAQc@Ee@?M@O@SFIBGBQHA@MFOJOLKJABMNKNKPEJEFQh@o@dCI`@wApFk@|BOh@K`@K`@GRGVOj@Mj@M`@K^Ol@GTMj@Ol@Oj@GVERCRA@EXCTCVAR?BAXAR?BAV?R?B?VBp@@R@n@DpANrE?HL|DJbDFjBJfDJ~DBp@F`B@VFxBc@BeAHY@s@FsAJQ@A?Q@}@Ha@BkAHS?KAMAuAS}@Qa@Ie@Ge@AQ?[Bc@BsDVYBI?mCReAHA?c@BeAHs@DyDVY@wBPwMz@SB[BmAFcCPe@B]@MAYA_@EqAQ]Ea@Ee@KQEKGC?UKGEMIQKKGSMEAUMEAOGQCCAUCIAc@C_@CCAc@E_@Ee@EOCE?c@Ew@IMAQCUCQAM?E?K?Q?[@G@c@@U@M@c@@c@Bc@@c@Bc@@c@Bc@@c@Bc@@u@Bs@Bg@Ba@@U@K?M?SASCSGUI]QMKMIOQIIQSQOKKc@g@o@s@IISSY[AAUSGEQM_@Qe@MSE[Co@?{@@E@e@AWCMCUEQIWMYSQMk@c@KG]YSOaFsDwB_BIGMI?AECoTePCA_CgB_@WyDuCyKgIIEeHiFEEiCoBiE_DKGaBoAmA}@kBwAkBsAo@g@mA{@kCqBy@k@QOOKQKOIQGOEOEQCQCQ?O?e@B_@B{AJmAHK@mCPyAJG?}@HgAFk@D_AFk@DYqGCo@OgDEkAEq@Cm@?AKwBGaBGaBGiACo@IcBAWMoCEmAEgAGgACu@CY?I{Dg@_BSYEeCa@OC_AM}@MGA[EcBWWCOCcC]UCICWCwDg@iBYc@GiBWgAOeAQc@GgAOuB[OCkG{@SCMCq@KIAaAOaAMq@KkAOiAM[GgC]c@ICAUCg@I_@GWIc@Q_Ak@g@[q@e@yBsAaBaA_Am@]UaC{Au@e@GEa@W}AaA_@UaBcAmBmAo@a@a@Y[Uw@i@GEGE_@UEAYMA?MGSEOESE]Gg@Gc@IeBW{B_@{AYCAeB[UEsAUa@Gc@IMAUEa@IgASmCc@kB[iF}@eGcAa@IgAQMCsB[O?kB]eASm@KqB]mB]_Dg@mB]qF_AsB]s@KWAU?QBWFUJOLIFg@f@cAlAgAtAIHuA~AkBvBy@z@QLMFCBUJODc@DWASESEYIeAc@}@[aAa@a@Oa@OyEmBcDmAiAc@mCkAsBy@qBw@qB{@oAg@iCaAkHsCA?aIaDoCgAiAc@eHoC_Bo@eCcAi@Qa@M}@Wy@QUGc@Ic@Ia@Ic@Ia@Ic@IMCw@Oc@IOCSCCA]GE?IC]GcAQ{@QcDm@}@QaEu@uNiC_Ca@iDk@iB]_B[iIwAgGkAoCe@cF_AeIyA{JkBuGkAaAQ}AYqGkA}Du@m@M_@GSCYCk@Cc@A{AEcACyIS_HQc@AeGOeACMAeEKg@AyBGg@AgACcAEiBEq@?k@@e@@aADA?kADsAFaBHwCJ}CNsAHcAFA?a@BA?S@}@Fm@B{BHa@BA?mCJc@BW@wBJs@BC@C?G?S@S?SAOAQCOCOEOGSGe@UcAg@o@[q@[k@YaCgAUKoAm@IEcAe@ECi@QsBw@iDqAwAk@]MyBy@m@UiAc@s@YkDoAo@Wq@W_Bm@}B}@e@QgBo@_@Oa@Qq@Ww@Y_A]IEm@Ss@SmEcA}IqBeBa@c@Ie@MwBg@aFiAgBa@oCm@kAYA?mGyAwHeBuCq@WEDk@D_ABSBo@PiCl@eKVaEDq@XuETmDf@iIL_CTeDH{@B]Hk@L{@Lk@Ji@Py@@CP{@BOLk@Nm@?ELg@`B{HJa@`@oBXsADS\\}An@wCNs@?CPs@Z{ALk@Z{AfBkIj@gC?Cl@kC@E\\aBt@oDd@}BTuAbBkPBWJoA^iDhAmLP_BTgC`@wDrAcNRkBPiBFm@Fa@F]F[DODOBKDOJYJ]Te@JSLUHODGJMPUVWRSX[`AcAr@{@^c@n@q@p@u@Z[d@e@fBeB^]hAkAfAgALOb@c@f@e@tB_CFGb@e@zA_Bf@g@NOTUVY~@aAvC{Cb@g@n@q@hAiA|AaBl@o@\\]VWT[TYNWLUJOLYTg@HUTw@Lc@Hc@Fe@F_@B[D_@@]@Y@Y@]?a@?o@?}@?G?aB?iF?E?c@?_A@e@@]@_@De@@MFi@F]F[F]J[BMNe@HQHUFOFMFKHMR[NSX_@FGLMPOZWRKTMRKVKRIPE`@K`@GbAQtAUzDo@vB]rAU"}